{
  "url": "https://www.airbus.com/space.html",
  "requestedUrl": "https://www.airbus.com/space.html",
  "timestamp": 1630019555782,
  "ranks": {
    "hundos": 2,
    "performance": 2,
    "accessibility": 2,
    "cumulative": 2
  },
  "lighthouse": {
    "version": "8.3.0",
    "performance": 0.14,
    "accessibility": 0.82,
    "bestPractices": 0.53,
    "seo": 0.77,
    "total": 226
  },
  "firstContentfulPaint": 5483.574,
  "firstMeaningfulPaint": 5996.378999999999,
  "speedIndex": 25370.388557988812,
  "largestContentfulPaint": 9038.392999999998,
  "totalBlockingTime": 4781.5,
  "cumulativeLayoutShift": 0.1242919921875,
  "timeToInteractive": 32510.444000000003,
  "maxPotentialFirstInputDelay": 1571,
  "timeToFirstByte": 3.4459999999999695,
  "weight": {
    "summary": "326 requests • 6,038 KiB",
    "total": 6182696,
    "image": 3316390,
    "imageCount": 135,
    "script": 1790005,
    "scriptCount": 75,
    "document": 73769,
    "font": 177511,
    "fontCount": 7,
    "stylesheet": 763839,
    "stylesheetCount": 30,
    "thirdParty": 4482831,
    "thirdPartyCount": 255
  },
  "run": {
    "number": 1,
    "total": 1
  },
  "axe": {
    "passes": 1379,
    "violations": 86
  },
  "name": "Airbus Space Unit"
}